ezai/__init__.py
ezai/configs.py
ezai/fs.py
ezai/res.py
ezai/version.txt
ezai/env/__init__.py
ezai/env/bandit.py
ezai/env/env_util.py
ezai/image/__init__.py
ezai/image/cv2_util.py
ezai/image/np_util.py
ezai/image/rw.py
ezai/util/__init__.py
ezai/util/archive.py
ezai/util/dict.py
ezai/util/filesys.py
ezai/util/fmt.py
ezai/util/json.py
ezai-0.0.2.dist-info/METADATA
ezai-0.0.2.dist-info/WHEEL
ezai-0.0.2.dist-info/entry_points.txt
ezai-0.0.2.dist-info/top_level.txt
ezai-0.0.2.dist-info/RECORD
