Metadata-Version: 2.1
Name: ezai
Version: 0.0.2
Summary: Easy AI Toolkit
Author: Armando Fandango
Author-email: armando@cortixly.ai
License: UNKNOWN
Platform: UNKNOWN
Classifier: Programming Language :: Python :: 3
Classifier: License :: OSI Approved :: Apache Software License
Classifier: Operating System :: OS Independent
Classifier: Topic :: Scientific/Engineering
Classifier: Topic :: Scientific/Engineering :: Mathematics
Classifier: Topic :: Scientific/Engineering :: Artificial Intelligence
Classifier: Topic :: Software Development
Classifier: Topic :: Software Development :: Libraries
Classifier: Intended Audience :: Developers
Classifier: Intended Audience :: Education
Classifier: Intended Audience :: Science/Research
Requires-Python: >=3.8
Requires-Dist: numpy
Requires-Dist: pytest
Requires-Dist: click
